easycreditscoring/__init__.py
easycreditscoring/src/__init__.py
easycreditscoring/src/data_cleaning.py
easycreditscoring/src/economy.py
easycreditscoring/src/ensembling.py
easycreditscoring/src/modelzoo.py
easycreditscoring-0.0.4.dist-info/LICENSE.txt
easycreditscoring-0.0.4.dist-info/METADATA
easycreditscoring-0.0.4.dist-info/WHEEL
easycreditscoring-0.0.4.dist-info/top_level.txt
easycreditscoring-0.0.4.dist-info/RECORD
